handyhelpers/__init__.py
handyhelpers/apps.py
handyhelpers/checks.py
handyhelpers/context_processors.py
handyhelpers/drf_permissions.py
handyhelpers/forms.py
handyhelpers/lookups.py
handyhelpers/managers.py
handyhelpers/models.py
handyhelpers/permissions.py
handyhelpers/querysets.py
handyhelpers/urls.py
handyhelpers/management/__init__.py
handyhelpers/management/commands/__init__.py
handyhelpers/management/commands/_private.py
handyhelpers/management/commands/add_superuser.py
handyhelpers/management/commands/add_user.py
handyhelpers/management/commands/generate_admin.py
handyhelpers/management/commands/generate_drf.py
handyhelpers/management/commands/generate_unittests.py
handyhelpers/management/commands/admin_templates/admin.jinja
handyhelpers/management/commands/drf_templates/apis_template.jinja
handyhelpers/management/commands/drf_templates/apis_template_filters.jinja
handyhelpers/management/commands/drf_templates/serializers_template.jinja
handyhelpers/management/commands/drf_templates/serializers_template_set_fields.jinja
handyhelpers/management/commands/drf_templates/urls_template.jinja
handyhelpers/management/commands/unittest_templates/model_crud.jinja
handyhelpers/management/commands/unittest_templates/model_crud_update_all_fields.jinja
handyhelpers/mixins/__init__.py
handyhelpers/mixins/form_mixins.py
handyhelpers/mixins/view_mixins.py
handyhelpers/mixins/viewset_mixins.py
handyhelpers/static/handyhelpers/css/handyhelper-cards.css
handyhelpers/static/handyhelpers/css/zoom-cards.css
handyhelpers/static/handyhelpers/css/zoom-groups.css
handyhelpers/static/handyhelpers/js/zoom-cards.js
handyhelpers/static/node_modules/chart.js/LICENSE.md
handyhelpers/static/node_modules/chart.js/README.md
handyhelpers/static/node_modules/chart.js/bower.json
handyhelpers/static/node_modules/chart.js/composer.json
handyhelpers/static/node_modules/chart.js/package.json
handyhelpers/static/node_modules/chart.js/dist/Chart.bundle.js
django_handyhelpers-0.1.26.dist-info/LICENSE
django_handyhelpers-0.1.26.dist-info/METADATA
django_handyhelpers-0.1.26.dist-info/WHEEL
django_handyhelpers-0.1.26.dist-info/top_level.txt
django_handyhelpers-0.1.26.dist-info/RECORD
