Metadata-Version: 2.1
Name: django-handyhelpers
Version: 0.1.26
Summary: A collection of handy utilities to support django operations
Home-page: https://github.com/davidslusser/django-handyhelpers
Download-URL: https://github.com/davidslusser/django-handyhelpers/archive/0.1.26.tar.gz
Author: David Slusser
Author-email: dbslusser@gmail.com
License: GPL-3.0
Keywords: django,helpers,handyhelpers
Classifier: Environment :: Web Environment
Classifier: Framework :: Django :: 3.2
Classifier: Intended Audience :: Developers
Classifier: Operating System :: OS Independent
Classifier: Programming Language :: Python :: 3
Classifier: Topic :: Internet :: WWW/HTTP
Classifier: Topic :: Internet :: WWW/HTTP :: Dynamic Content
Classifier: Topic :: Software Development :: Libraries :: Python Modules
License-File: LICENSE
Requires-Dist: Django
Requires-Dist: djangorestframework
Requires-Dist: djangorestframework-filters (==1.0.0.dev0)
Requires-Dist: drf-dynamic-fields
Requires-Dist: Jinja2
Requires-Dist: MarkupSafe
Requires-Dist: pytz
Requires-Dist: sqlparse
Requires-Dist: xlwt (==1.3.0)
